api/__init__.py
api/_code.py
superbrowserapi/__init__.py
superbrowserapi/_code.py
superbrowserapi-0.0.6.dist-info/METADATA
superbrowserapi-0.0.6.dist-info/WHEEL
superbrowserapi-0.0.6.dist-info/top_level.txt
superbrowserapi-0.0.6.dist-info/RECORD
