Metadata-Version: 2.1
Name: superbrowserapi
Version: 0.0.6
Summary: 整合紫鸟操作店铺API
Home-page: https://github.com/lzzkey
Author: lzzkey
Author-email: 617692766@qq.com
Classifier: Programming Language :: Python :: 3.7
Classifier: License :: OSI Approved :: MIT License
Classifier: Operating System :: OS Independent
Requires-Python: >=3.7
Requires-Dist: requests
Requires-Dist: uuid
Requires-Dist: psutil
